qfix/__init__.py
qfix-0.0.1.dist-info/METADATA
qfix-0.0.1.dist-info/WHEEL
qfix-0.0.1.dist-info/entry_points.txt
qfix-0.0.1.dist-info/licenses/LICENCE
qfix-0.0.1.dist-info/RECORD
