Metadata-Version: 2.4
Name: qfix
Version: 0.0.1
Summary: Quantum Error Correction tools in Quantinuum ecosystem.
Author-email: Seyon Sivarajah <seyon.sivarajah@quantinuum.com>
License:                                  Apache License
License-File: LICENCE
Requires-Python: >=3.12
